README.txt
setup.cfg
setup.py
InPlace.egg-info/PKG-INFO
InPlace.egg-info/SOURCES.txt
InPlace.egg-info/dependency_links.txt
InPlace.egg-info/entry_points.txt
InPlace.egg-info/not-zip-safe
InPlace.egg-info/paster_plugins.txt
InPlace.egg-info/requires.txt
InPlace.egg-info/sqlobject.txt
InPlace.egg-info/top_level.txt
inplace/__init__.py
inplace/release.py
inplace/widgets.py
inplace/static/images/favicon.ico
inplace/static/images/tg_under_the_hood.png
inplace/static/images/under_the_hood_blue.png
inplace/static/javascript/inplace.js
inplace/templates/__init__.py